tenable_aws_sechub/__init__.py
tenable_aws_sechub/cli.py
tenable_aws_sechub/finding.py
tenable_aws_sechub/transform.py
tenable_aws_sechub/version.py
tenable_aws_sechub-2.2.1.dist-info/METADATA
tenable_aws_sechub-2.2.1.dist-info/WHEEL
tenable_aws_sechub-2.2.1.dist-info/entry_points.txt
tenable_aws_sechub-2.2.1.dist-info/top_level.txt
tenable_aws_sechub-2.2.1.dist-info/RECORD
