Metadata-Version: 2.1
Name: tenable_aws_sechub
Version: 2.2.1
Summary: Tenable Vulnerability Management to AWS Security Hub
Author-email: "Tenable, Inc." <smcgrath@tenable.com>
License: MIT License
Project-URL: Homepage, https://github.com/tenable/Security-Hub
Project-URL: Repository, https://github.com/tenable/Security-Hub
Project-URL: Issues, https://github.com/tenable/Security-Hub/issues
Project-URL: Changelog, https://github.com/tenable/Security-Hub/blob/main/CHANGELOG.md
Keywords: tenable,tenable vulnerability management,tenable security center,tenable.io,tenable.sc,aws,security hub
Classifier: Development Status :: 5 - Production/Stable
Classifier: Intended Audience :: Information Technology
Classifier: Topic :: System :: Systems Administration
Classifier: License :: OSI Approved :: MIT License
Classifier: Programming Language :: Python :: 3.10
Classifier: Programming Language :: Python :: 3.11
Classifier: Programming Language :: Python :: 3.12
Requires-Dist: arrow >=1.3.0
Requires-Dist: restfly >=1.4.5
Requires-Dist: typer >=0.9.0
Requires-Dist: tomlkit >=0.12.4
Requires-Dist: rich >=13.3.1
Requires-Dist: boto3 >=1.34.68
Requires-Dist: pytenable >=1.5.0
